Multiprogramming/__init__.py
multiprogramming-0.0.1.dist-info/LICENSE
multiprogramming-0.0.1.dist-info/METADATA
multiprogramming-0.0.1.dist-info/WHEEL
multiprogramming-0.0.1.dist-info/top_level.txt
multiprogramming-0.0.1.dist-info/RECORD
