Metadata-Version: 2.1
Name: multiprogramming
Version: 0.0.1
Summary: A package for multiprogramming algorithm
Home-page: https://github.com/peachnuts/Multiprogramming
Author: Siyuan Niu
Author-email: siyuan.niu@lirmm.fr
License: UNKNOWN
Platform: UNKNOWN
Classifier: Programming Language :: Python :: 3
Classifier: License :: OSI Approved :: MIT License
Classifier: Operating System :: OS Independent
Requires-Python: >=3.7
Requires-Dist: numpy
Requires-Dist: qiskit
Requires-Dist: networkx
